## æ”¯æŒæƒ…å†µæµ‹è¯•

æµ‹è¯•å¹³å°ï¼š Ubuntu 20.04.3 LTS AMD64 (WSL 1)
ç”¨äºè¿›è¡Œæµ‹è¯•çš„ Python ç‰ˆæœ¬è¯¦ç»†ä¿¡æ¯ï¼š

```plaintext
Python 3.9.19 (main, Mar 20 2024, 18:08:17) [GCC 9.4.0] on linux
```

è¿è¡Œé‡ç°é¡¹ç›®è‡ªèº«æµ‹è¯•çš„ç»“æœä¸ Python 3.8 ä¸‹çš„æµ‹è¯•ç»“æœå®Œå…¨ç›¸åŒï¼ŒåŒ…æ‹¬è­¦å‘Šä¿¡æ¯ã€‚

## æ‰‹å·¥æµ‹è¯•å‘½ä»¤è¡Œé€‰é¡¹åŠŸèƒ½

ç”±äº `--è¯­æ³•æ ‘` å‚æ•°çš„å·®å¼‚å·²ç»åœ¨ä¸‹æ–‡è¯´æ˜ï¼Œä¸”é™¤äº† `--åæ±‡ç¼–` é€‰é¡¹ä»¥å¤–ï¼Œå…¶ä»–é€‰é¡¹çš„è¡Œä¸ºåœ¨ Py3.9 å’Œ Py3.8 ç‰ˆæœ¬é—´æ— æ˜æ˜¾å·®å¼‚ï¼Œæ•…ä»…åˆ—å‡º `--åæ±‡ç¼–` é€‰é¡¹çš„è¾“å‡ºç»“æœã€‚

### åæ±‡ç¼–å­—èŠ‚ç æµ‹è¯•

ä½¿ç”¨`py3.8æ”¯æŒ.md`æ–‡ä»¶ä¸­ç»™å‡ºçš„`åæ±‡ç¼–æµ‹è¯•.ul`è¿è¡Œ`æœ¨å…° --åæ±‡ç¼– åæ±‡ç¼–æµ‹è¯•.ul`ï¼Œç»“æœå¦‚ä¸‹ï¼š

```plaintext
  1           0 LOAD_CONST               0 (0)
              2 STORE_NAME               0 (i)

  3     >>    4 LOAD_NAME                0 (i)
              6 LOAD_CONST               1 (10)
              8 COMPARE_OP               1 (<=)
             10 POP_JUMP_IF_FALSE       80

  4          12 LOAD_NAME                0 (i)
             14 LOAD_CONST               2 (1)
             16 INPLACE_ADD
             18 STORE_NAME               0 (i)

  6          20 SETUP_FINALLY           18 (to 40)

  7          22 LOAD_NAME                1 (__rem__)
             24 LOAD_NAME                0 (i)
             26 LOAD_CONST               3 (2)
             28 CALL_FUNCTION            2
             30 POP_JUMP_IF_FALSE       36

  8          32 POP_BLOCK
             34 JUMP_ABSOLUTE            4
        >>   36 POP_BLOCK
             38 JUMP_FORWARD            30 (to 70)

 10     >>   40 POP_TOP
             42 STORE_NAME               2 (Exception)
             44 POP_TOP
             46 SETUP_FINALLY           12 (to 60)
             48 POP_BLOCK
             50 POP_EXCEPT
             52 LOAD_CONST               4 (None)
             54 STORE_NAME               2 (Exception)
             56 DELETE_NAME              2 (Exception)
             58 JUMP_FORWARD            10 (to 70)
        >>   60 LOAD_CONST               4 (None)
             62 STORE_NAME               2 (Exception)
             64 DELETE_NAME              2 (Exception)
             66 RERAISE
             68 RERAISE

 12     >>   70 LOAD_NAME                3 (println)
             72 LOAD_NAME                0 (i)
             74 CALL_FUNCTION            1
             76 POP_TOP
             78 JUMP_ABSOLUTE            4
        >>   80 LOAD_CONST               4 (None)
             82 RETURN_VALUE
```

å…¶ä¸­æ–°å‡ºç°äº†`RERAISE`æ“ä½œç ï¼Œå…³äºå…¶å…·ä½“çš„ä½œç”¨ä»¥åŠå…¶å®ƒå·®åˆ«ï¼Œå¯ä»¥å‚è€ƒ [dis --- Python å­—èŠ‚ç åæ±‡ç¼–å™¨ â€” Python 3.9.18 æ–‡æ¡£](https://docs.python.org/zh-cn/3.9/library/dis.html#opcode-RERAISE)ã€‚

### è¯­æ³•æ ‘èŠ‚ç‚¹å·®å¼‚

Python 3.9 ä¸­ï¼Œå‡½æ•°è°ƒç”¨æ—¶çš„[å…³é”®å­—å‚æ•°](https://docs.python.org/zh-cn/3.9/glossary.html#term-argument)å¿…é¡»æä¾›`lineno`ä¸`col_offset`å±æ€§ï¼Œå¦åˆ™ä¼šå‡ºç°å½¢å¦‚å¦‚ä¸‹çš„å¼‚å¸¸ï¼š`ç±»å‹é”™è¯¯ï¼šrequired field "lineno" missing from keyword`ã€‚

----

(py39) (base) xuanwu@XuantekiMBP åˆ·é¢˜ % time æœ¨å…° å®ç”¨/æ•°å­¦/äºŒåå››ç‚¹.ul
^CTraceback (most recent call last):
  File "/Users/xuanwu/opt/anaconda3/lib/python3.8/site-packages/æœ¨å…°/ç¯å¢ƒ.py", line 167, in è‡ªå®šä¹‰å¯¼å…¥
    return åŠ è½½æœ¨å…°æ¨¡å—(åç§°, å…¨å±€, æºè‡ª, ç›®å½•ç›¸å¯¹å±‚æ¬¡)
  File "/Users/xuanwu/opt/anaconda3/lib/python3.8/site-packages/æœ¨å…°/ç¯å¢ƒ.py", line 59, in åŠ è½½æœ¨å…°æ¨¡å—
    å¯æ‰§è¡Œç  = åˆ†æå¹¶ç¼–è¯‘(æœ¨å…°æºç è·¯å¾„)
  File "/Users/xuanwu/opt/anaconda3/lib/python3.8/site-packages/æœ¨å…°/ç¯å¢ƒ.py", line 49, in åˆ†æå¹¶ç¼–è¯‘
    with open(æºç æ–‡ä»¶å, 'r', encoding='utf-8') as æ–‡ä»¶:
FileNotFoundError: [Errno 2] No such file or directory: 'numexpr.ul'

During handling of the above exception, another exception occurred:

Traceback (most recent call last):
  File "/Users/xuanwu/opt/anaconda3/lib/python3.8/site-packages/numpy/__init__.py", line 327, in <module>
    __mkl_version__ = "{MajorVersion}.{MinorVersion}.{UpdateVersion}".format(**mkl.get_version())
KeyboardInterrupt
 ğŸ˜° ImportErrorï¼šnumpy.core.multiarray failed to import
â€œ/Users/xuanwu/opt/anaconda3/lib/python3.8/site-packages/numexpr/__init__.pyâ€ç¬¬26è¡Œï¼šfrom numexpr.interpreter import MAX_THREADS, use_vml, __BLOCK_SIZE1__
è°ƒç”¨å±‚çº§å¦‚ä¸‹
è§ç¬¬1è¡Œï¼šusing numexpr
æœ¨å…° å®ç”¨/æ•°å­¦/äºŒåå››ç‚¹.ul  1.03s user 0.06s system 5% cpu 18.319 total